better_singleton/__init__.py
better_singleton/singleton.py
better_singleton-1.0.1.dist-info/LICENSE.md
better_singleton-1.0.1.dist-info/METADATA
better_singleton-1.0.1.dist-info/WHEEL
better_singleton-1.0.1.dist-info/RECORD
