Metadata-Version: 2.1
Name: better-singleton
Version: 1.0.1
Summary: A clean, transparent and easy to use python singleton wrapper.
Home-page: https://github.com/StephanSchmiedmayer/SingletonPython
Author: Stephan Schmiedmayer
Author-email: 56692976+StephanSchmiedmayer@users.noreply.github.com
Requires-Python: >=3.11,<4.0
Classifier: Programming Language :: Python :: 3
Classifier: Programming Language :: Python :: 3.11
Project-URL: Repository, https://github.com/StephanSchmiedmayer/SingletonPython
